{
  "title": "Autocomplete Product Search",
  "group": "Products",
  "description": "Generate suggestions for grocery products based on a (partial) query. The matches will be found by looking in the title only.",
  "endpoint_url": "https://api.spoonacular.com/food/products/suggest",
  "endpoint_method": "GET",
  "parameters": {
    "query": {
      "Name": "query",
      "Type": "string",
      "Example": "chicke",
      "Description": "The (partial) search query."
    },
    "number": {
      "Name": "number",
      "Type": "number",
      "Example": "10",
      "Description": "The number of results to return (between 1 and 25)."
    }
  },
  "code_examples": [
    {
      "language": "json",
      "code": "{\n    \"results\": [\n        {\n            \"id\": 208698,\n            \"title\": \"buddig premium deli chicken breast - rotisserie flavored\"\n        },\n        {\n            \"id\": 41291,\n            \"title\": \"tyson all natural chicken breasts tenderloins\"\n        }\n    ]\n}"
    }
  ],
  "quota": "Calling this endpoint requires 0.1 points. Learn more about quotas."
}